Workbook
Name CurMonth: Inputs!$B$4
Name ThrPct: Inputs!$B$5
Name ThrAmt: Inputs!$B$6

Sheet Cover
A1: Northwind Supply Co. - FY2026 Budget vs. Actual & Rolling Forecast
A2: Illustrative FP&A model. All figures in $ thousands. Data is fictional.
A4: Purpose | B4: Monthly and YTD budget-to-actual reporting, variance flags, a rolling 9+3 forecast, and a management P&L.
A5: How to use | B5: Close a month by entering actuals on the Actuals sheet and setting the closed month on Inputs. Everything else recalculates.
A6: Conventions | B6: Blue = hard-coded input; black = formula. Variances are shown as favorable (+) / unfavorable (-) for both revenue and costs.
A7: Inputs | B7: Closed month, variance flag thresholds (% and $).
A8: Budget / Actuals | B8: 21 line items x 12 months by department and category (Revenue, COGS, Opex).
A9: BvA | B9: Current month and YTD budget vs. actual by line, with variance % and automatic flags.
A10: Forecast | B10: Closed months = actuals; open months forecast by line method: Attainment (budget x YTD actual/budget), Run-rate (avg of last 3 closed months) or Budget.
A11: P&L Summary | B11: Revenue to EBITDA: YTD budget vs. actual and FY budget vs. forecast, with margins.
A12: Mgmt Report | B12: Key metrics and variance commentary for leadership.
A13: Checks | B13: Integrity checks; all must show TRUE.

Sheet Inputs
A1: Inputs
A2: Change these to close a new month or tighten variance flags.
A4: Last closed month (1-12) | B4: 9
A5: Variance flag threshold, % | B5: 0.05
A6: Variance flag threshold, $000s | B6: 25
A8: Closed month name | B8: =INDEX({"Jan","Feb","Mar","Apr","May","Jun","Jul","Aug","Sep","Oct","Nov","Dec"},CurMonth)

Sheet Budget
A1: Northwind Supply Co. - FY2026 Budget ($000s)
A2: Approved FY budget by month.
A3: ID | B3: Line item | C3: Department | D3: Category | E3: 1 | F3: 2 | G3: 3 | H3: 4 | I3: 5 | J3: 6 | K3: 7 | L3: 8 | M3: 9 | N3: 10 | O3: 11 | P3: 12 | Q3: FY Total
A4: REV-A | B4: Industrial Supplies | C4: Sales | D4: Revenue | E4: 1800 | F4: 1800 | G4: 2040 | H4: 2040 | I4: 2160 | J4: 2160 | K4: 1920 | L4: 1920 | M4: 2040 | N4: 2160 | O4: 2040 | P4: 1920 | Q4: =SUM(E4:P4)
A5: REV-B | B5: Safety Equipment | C5: Sales | D5: Revenue | E5: 1050 | F5: 1050 | G5: 1190 | H5: 1190 | I5: 1260 | J5: 1260 | K5: 1120 | L5: 1120 | M5: 1190 | N5: 1260 | O5: 1190 | P5: 1120 | Q5: =SUM(E5:P5)
A6: REV-C | B6: Services & Installation | C6: Sales | D6: Revenue | E6: 750 | F6: 750 | G6: 850 | H6: 850 | I6: 900 | J6: 900 | K6: 800 | L6: 800 | M6: 850 | N6: 900 | O6: 850 | P6: 800 | Q6: =SUM(E6:P6)
A7: COGS-A | B7: Cost of Goods - Industrial Supplies | C7: Operations | D7: COGS | E7: 1188 | F7: 1188 | G7: 1346.4 | H7: 1346.4 | I7: 1425.6 | J7: 1425.6 | K7: 1267.2 | L7: 1267.2 | M7: 1346.4 | N7: 1425.6 | O7: 1346.4 | P7: 1267.2 | Q7: =SUM(E7:P7)
A8: COGS-B | B8: Cost of Goods - Safety Equipment | C8: Operations | D8: COGS | E8: 630 | F8: 630 | G8: 714 | H8: 714 | I8: 756 | J8: 756 | K8: 672 | L8: 672 | M8: 714 | N8: 756 | O8: 714 | P8: 672 | Q8: =SUM(E8:P8)
A9: COGS-C | B9: Cost of Services & Installation | C9: Operations | D9: COGS | E9: 337.5 | F9: 337.5 | G9: 382.5 | H9: 382.5 | I9: 405 | J9: 405 | K9: 360 | L9: 360 | M9: 382.5 | N9: 405 | O9: 382.5 | P9: 360 | Q9: =SUM(E9:P9)
A10: COGS-FRT | B10: Freight & Logistics | C10: Operations | D10: COGS | E10: 99.8 | F10: 99.8 | G10: 113.1 | H10: 113.1 | I10: 119.7 | J10: 119.7 | K10: 106.4 | L10: 106.4 | M10: 113.1 | N10: 119.7 | O10: 113.1 | P10: 106.4 | Q10: =SUM(E10:P10)
A11: SAL-SALES | B11: Salaries & Benefits | C11: Sales | D11: Opex | E11: 200 | F11: 200 | G11: 200 | H11: 200 | I11: 200 | J11: 200 | K11: 200 | L11: 200 | M11: 200 | N11: 200 | O11: 200 | P11: 200 | Q11: =SUM(E11:P11)
A12: COMM-SALES | B12: Sales Commissions | C12: Sales | D12: Opex | E12: 108 | F12: 108 | G12: 122.4 | H12: 122.4 | I12: 129.6 | J12: 129.6 | K12: 115.2 | L12: 115.2 | M12: 122.4 | N12: 129.6 | O12: 122.4 | P12: 115.2 | Q12: =SUM(E12:P12)
A13: TE-SALES | B13: Travel & Entertainment | C13: Sales | D13: Opex | E13: 30 | F13: 30 | G13: 30 | H13: 30 | I13: 30 | J13: 30 | K13: 30 | L13: 30 | M13: 30 | N13: 30 | O13: 30 | P13: 30 | Q13: =SUM(E13:P13)
A14: SAL-MKT | B14: Salaries & Benefits | C14: Marketing | D14: Opex | E14: 80 | F14: 80 | G14: 80 | H14: 80 | I14: 80 | J14: 80 | K14: 80 | L14: 80 | M14: 80 | N14: 80 | O14: 80 | P14: 80 | Q14: =SUM(E14:P14)
A15: ADS-MKT | B15: Digital Advertising | C15: Marketing | D15: Opex | E15: 60 | F15: 60 | G15: 60 | H15: 60 | I15: 60 | J15: 60 | K15: 60 | L15: 60 | M15: 60 | N15: 60 | O15: 60 | P15: 60 | Q15: =SUM(E15:P15)
... A24: SW-IT | B24: Software & Subscriptions | C24: IT | D24: Opex | E24: 45 | F24: 45 | G24: 45 | H24: 45 | I24: 45 | J24: 45 | K24: 45 | L24: 45 | M24: 45 | N24: 45 | O24: 45 | P24: 45 | Q24: =SUM(E24:P24)

Sheet Actuals
A1: Northwind Supply Co. - FY2026 Actuals ($000s)
A2: Closed actuals from the general ledger; open months left blank.
A3: ID | B3: Line item | C3: Department | D3: Category | E3: 1 | F3: 2 | G3: 3 | H3: 4 | I3: 5 | J3: 6 | K3: 7 | L3: 8 | M3: 9 | N3: 10 | O3: 11 | P3: 12 | Q3: FY Total
A4: REV-A | B4: Industrial Supplies | C4: Sales | D4: Revenue | E4: 1778.6 | F4: 1806.5 | G4: 1982 | H4: 2166 | I4: 2267.9 | J4: 2236.6 | K4: 1987.5 | L4: 2005.9 | M4: 2113.1 | Q4: =SUM(E4:P4)
A5: REV-B | B5: Safety Equipment | C5: Sales | D5: Revenue | E5: 1049 | F5: 1048.7 | G5: 1192.9 | H5: 1179 | I5: 1252.4 | J5: 1092.5 | K5: 961.3 | L5: 943.3 | M5: 1016.1 | Q5: =SUM(E5:P5)
A6: REV-C | B6: Services & Installation | C6: Sales | D6: Revenue | E6: 757.2 | F6: 770.5 | G6: 840.9 | H6: 867.2 | I6: 883.4 | J6: 902.4 | K6: 786 | L6: 816.2 | M6: 860.6 | Q6: =SUM(E6:P6)
A7: COGS-A | B7: Cost of Goods - Industrial Supplies | C7: Operations | D7: COGS | E7: 1169 | F7: 1187.9 | G7: 1313.4 | H7: 1439.6 | I7: 1499.3 | J7: 1468.7 | K7: 1303.1 | L7: 1339.2 | M7: 1401.3 | Q7: =SUM(E7:P7)
A8: COGS-B | B8: Cost of Goods - Safety Equipment | C8: Operations | D8: COGS | E8: 642.3 | F8: 645.1 | G8: 725 | H8: 712.1 | I8: 747.4 | J8: 660.7 | K8: 574.7 | L8: 565.9 | M8: 608.2 | Q8: =SUM(E8:P8)
A9: COGS-C | B9: Cost of Services & Installation | C9: Operations | D9: COGS | E9: 338.1 | F9: 344 | G9: 375.5 | H9: 385.8 | I9: 394.6 | J9: 410.3 | K9: 352 | L9: 368.1 | M9: 383.5 | Q9: =SUM(E9:P9)
A10: COGS-FRT | B10: Freight & Logistics | C10: Operations | D10: COGS | E10: 101.2 | F10: 99.3 | G10: 132.6 | H10: 138.8 | I10: 145.2 | J10: 136.6 | K10: 123.4 | L10: 121.6 | M10: 131.2 | Q10: =SUM(E10:P10)
A11: SAL-SALES | B11: Salaries & Benefits | C11: Sales | D11: Opex | E11: 200.4 | F11: 198.8 | G11: 199.3 | H11: 199.8 | I11: 199.1 | J11: 200.7 | K11: 200.6 | L11: 198 | M11: 198.2 | Q11: =SUM(E11:P11)
A12: COMM-SALES | B12: Sales Commissions | C12: Sales | D12: Opex | E12: 107.1 | F12: 109 | G12: 119.2 | H12: 125 | I12: 129.5 | J12: 126.9 | K12: 113.1 | L12: 112.6 | M12: 121.4 | Q12: =SUM(E12:P12)
A13: TE-SALES | B13: Travel & Entertainment | C13: Sales | D13: Opex | E13: 30.7 | F13: 31.7 | G13: 28.8 | H13: 26.6 | I13: 30.2 | J13: 29.1 | K13: 30 | L13: 32.5 | M13: 28.3 | Q13: =SUM(E13:P13)
A14: SAL-MKT | B14: Salaries & Benefits | C14: Marketing | D14: Opex | E14: 80.4 | F14: 79.8 | G14: 79.7 | H14: 80.4 | I14: 80.3 | J14: 80.6 | K14: 80.1 | L14: 80.6 | M14: 79.9 | Q14: =SUM(E14:P14)
A15: ADS-MKT | B15: Digital Advertising | C15: Marketing | D15: Opex | E15: 62 | F15: 56.5 | G15: 58.9 | H15: 65.1 | I15: 62 | J15: 64.3 | K15: 57.6 | L15: 54.1 | M15: 63.6 | Q15: =SUM(E15:P15)
... A24: SW-IT | B24: Software & Subscriptions | C24: IT | D24: Opex | E24: 44.4 | F24: 44.4 | G24: 43.6 | H24: 44 | I24: 43.6 | J24: 44.4 | K24: 44.5 | L24: 44.5 | M24: 45.3 | Q24: =SUM(E24:P24)

Sheet BvA
A1: Budget vs. Actual ($000s)
A2: Favorable variance = actual revenue above budget, or actual cost below budget. | F2: ="Month: "&Inputs!B8
A3: ID | B3: Line item | C3: Department | D3: Category | E3: Month Budget | F3: Month Actual | G3: Month Var Fav/(Unfav) | H3: Month Var % | I3: YTD Budget | J3: YTD Actual | K3: YTD Var Fav/(Unfav) | L3: YTD Var % | M3: YTD Flag
A4: =Budget!A4 | B4: =Budget!B4 | C4: =Budget!C4 | D4: =Budget!D4 | E4: =INDEX(Budget!$E4:$P4,CurMonth) | F4: =INDEX(Actuals!$E4:$P4,CurMonth) | G4: =IF($D4="Revenue",F4-E4,E4-F4) | H4: =IF(E4=0,0,G4/ABS(E4)) | I4: =SUMPRODUCT(Budget!$E4:$P4*(Budget!$E$3:$P$3<=CurMonth)) | J4: =SUMPRODUCT(Actuals!$E4:$P4*(Budget!$E$3:$P$3<=CurMonth)) | K4: =IF($D4="Revenue",J4-I4,I4-J4) | L4: =IF(I4=0,0,K4/ABS(I4)) | M4: =IF(AND(ABS(L4)>=ThrPct,ABS(K4)>=ThrAmt),IF(K4<0,"Unfavorable","Favorable"),"")
A5: =Budget!A5 | B5: =Budget!B5 | C5: =Budget!C5 | D5: =Budget!D5 | E5: =INDEX(Budget!$E5:$P5,CurMonth) | F5: =INDEX(Actuals!$E5:$P5,CurMonth) | G5: =IF($D5="Revenue",F5-E5,E5-F5) | H5: =IF(E5=0,0,G5/ABS(E5)) | I5: =SUMPRODUCT(Budget!$E5:$P5*(Budget!$E$3:$P$3<=CurMonth)) | J5: =SUMPRODUCT(Actuals!$E5:$P5*(Budget!$E$3:$P$3<=CurMonth)) | K5: =IF($D5="Revenue",J5-I5,I5-J5) | L5: =IF(I5=0,0,K5/ABS(I5)) | M5: =IF(AND(ABS(L5)>=ThrPct,ABS(K5)>=ThrAmt),IF(K5<0,"Unfavorable","Favorable"),"")
A6: =Budget!A6 | B6: =Budget!B6 | C6: =Budget!C6 | D6: =Budget!D6 | E6: =INDEX(Budget!$E6:$P6,CurMonth) | F6: =INDEX(Actuals!$E6:$P6,CurMonth) | G6: =IF($D6="Revenue",F6-E6,E6-F6) | H6: =IF(E6=0,0,G6/ABS(E6)) | I6: =SUMPRODUCT(Budget!$E6:$P6*(Budget!$E$3:$P$3<=CurMonth)) | J6: =SUMPRODUCT(Actuals!$E6:$P6*(Budget!$E$3:$P$3<=CurMonth)) | K6: =IF($D6="Revenue",J6-I6,I6-J6) | L6: =IF(I6=0,0,K6/ABS(I6)) | M6: =IF(AND(ABS(L6)>=ThrPct,ABS(K6)>=ThrAmt),IF(K6<0,"Unfavorable","Favorable"),"")
A7: =Budget!A7 | B7: =Budget!B7 | C7: =Budget!C7 | D7: =Budget!D7 | E7: =INDEX(Budget!$E7:$P7,CurMonth) | F7: =INDEX(Actuals!$E7:$P7,CurMonth) | G7: =IF($D7="Revenue",F7-E7,E7-F7) | H7: =IF(E7=0,0,G7/ABS(E7)) | I7: =SUMPRODUCT(Budget!$E7:$P7*(Budget!$E$3:$P$3<=CurMonth)) | J7: =SUMPRODUCT(Actuals!$E7:$P7*(Budget!$E$3:$P$3<=CurMonth)) | K7: =IF($D7="Revenue",J7-I7,I7-J7) | L7: =IF(I7=0,0,K7/ABS(I7)) | M7: =IF(AND(ABS(L7)>=ThrPct,ABS(K7)>=ThrAmt),IF(K7<0,"Unfavorable","Favorable"),"")
A8: =Budget!A8 | B8: =Budget!B8 | C8: =Budget!C8 | D8: =Budget!D8 | E8: =INDEX(Budget!$E8:$P8,CurMonth) | F8: =INDEX(Actuals!$E8:$P8,CurMonth) | G8: =IF($D8="Revenue",F8-E8,E8-F8) | H8: =IF(E8=0,0,G8/ABS(E8)) | I8: =SUMPRODUCT(Budget!$E8:$P8*(Budget!$E$3:$P$3<=CurMonth)) | J8: =SUMPRODUCT(Actuals!$E8:$P8*(Budget!$E$3:$P$3<=CurMonth)) | K8: =IF($D8="Revenue",J8-I8,I8-J8) | L8: =IF(I8=0,0,K8/ABS(I8)) | M8: =IF(AND(ABS(L8)>=ThrPct,ABS(K8)>=ThrAmt),IF(K8<0,"Unfavorable","Favorable"),"")
A9: =Budget!A9 | B9: =Budget!B9 | C9: =Budget!C9 | D9: =Budget!D9 | E9: =INDEX(Budget!$E9:$P9,CurMonth) | F9: =INDEX(Actuals!$E9:$P9,CurMonth) | G9: =IF($D9="Revenue",F9-E9,E9-F9) | H9: =IF(E9=0,0,G9/ABS(E9)) | I9: =SUMPRODUCT(Budget!$E9:$P9*(Budget!$E$3:$P$3<=CurMonth)) | J9: =SUMPRODUCT(Actuals!$E9:$P9*(Budget!$E$3:$P$3<=CurMonth)) | K9: =IF($D9="Revenue",J9-I9,I9-J9) | L9: =IF(I9=0,0,K9/ABS(I9)) | M9: =IF(AND(ABS(L9)>=ThrPct,ABS(K9)>=ThrAmt),IF(K9<0,"Unfavorable","Favorable"),"")
A10: =Budget!A10 | B10: =Budget!B10 | C10: =Budget!C10 | D10: =Budget!D10 | E10: =INDEX(Budget!$E10:$P10,CurMonth) | F10: =INDEX(Actuals!$E10:$P10,CurMonth) | G10: =IF($D10="Revenue",F10-E10,E10-F10) | H10: =IF(E10=0,0,G10/ABS(E10)) | I10: =SUMPRODUCT(Budget!$E10:$P10*(Budget!$E$3:$P$3<=CurMonth)) | J10: =SUMPRODUCT(Actuals!$E10:$P10*(Budget!$E$3:$P$3<=CurMonth)) | K10: =IF($D10="Revenue",J10-I10,I10-J10) | L10: =IF(I10=0,0,K10/ABS(I10)) | M10: =IF(AND(ABS(L10)>=ThrPct,ABS(K10)>=ThrAmt),IF(K10<0,"Unfavorable","Favorable"),"")
A11: =Budget!A11 | B11: =Budget!B11 | C11: =Budget!C11 | D11: =Budget!D11 | E11: =INDEX(Budget!$E11:$P11,CurMonth) | F11: =INDEX(Actuals!$E11:$P11,CurMonth) | G11: =IF($D11="Revenue",F11-E11,E11-F11) | H11: =IF(E11=0,0,G11/ABS(E11)) | I11: =SUMPRODUCT(Budget!$E11:$P11*(Budget!$E$3:$P$3<=CurMonth)) | J11: =SUMPRODUCT(Actuals!$E11:$P11*(Budget!$E$3:$P$3<=CurMonth)) | K11: =IF($D11="Revenue",J11-I11,I11-J11) | L11: =IF(I11=0,0,K11/ABS(I11)) | M11: =IF(AND(ABS(L11)>=ThrPct,ABS(K11)>=ThrAmt),IF(K11<0,"Unfavorable","Favorable"),"")
A12: =Budget!A12 | B12: =Budget!B12 | C12: =Budget!C12 | D12: =Budget!D12 | E12: =INDEX(Budget!$E12:$P12,CurMonth) | F12: =INDEX(Actuals!$E12:$P12,CurMonth) | G12: =IF($D12="Revenue",F12-E12,E12-F12) | H12: =IF(E12=0,0,G12/ABS(E12)) | I12: =SUMPRODUCT(Budget!$E12:$P12*(Budget!$E$3:$P$3<=CurMonth)) | J12: =SUMPRODUCT(Actuals!$E12:$P12*(Budget!$E$3:$P$3<=CurMonth)) | K12: =IF($D12="Revenue",J12-I12,I12-J12) | L12: =IF(I12=0,0,K12/ABS(I12)) | M12: =IF(AND(ABS(L12)>=ThrPct,ABS(K12)>=ThrAmt),IF(K12<0,"Unfavorable","Favorable"),"")
A13: =Budget!A13 | B13: =Budget!B13 | C13: =Budget!C13 | D13: =Budget!D13 | E13: =INDEX(Budget!$E13:$P13,CurMonth) | F13: =INDEX(Actuals!$E13:$P13,CurMonth) | G13: =IF($D13="Revenue",F13-E13,E13-F13) | H13: =IF(E13=0,0,G13/ABS(E13)) | I13: =SUMPRODUCT(Budget!$E13:$P13*(Budget!$E$3:$P$3<=CurMonth)) | J13: =SUMPRODUCT(Actuals!$E13:$P13*(Budget!$E$3:$P$3<=CurMonth)) | K13: =IF($D13="Revenue",J13-I13,I13-J13) | L13: =IF(I13=0,0,K13/ABS(I13)) | M13: =IF(AND(ABS(L13)>=ThrPct,ABS(K13)>=ThrAmt),IF(K13<0,"Unfavorable","Favorable"),"")
A14: =Budget!A14 | B14: =Budget!B14 | C14: =Budget!C14 | D14: =Budget!D14 | E14: =INDEX(Budget!$E14:$P14,CurMonth) | F14: =INDEX(Actuals!$E14:$P14,CurMonth) | G14: =IF($D14="Revenue",F14-E14,E14-F14) | H14: =IF(E14=0,0,G14/ABS(E14)) | I14: =SUMPRODUCT(Budget!$E14:$P14*(Budget!$E$3:$P$3<=CurMonth)) | J14: =SUMPRODUCT(Actuals!$E14:$P14*(Budget!$E$3:$P$3<=CurMonth)) | K14: =IF($D14="Revenue",J14-I14,I14-J14) | L14: =IF(I14=0,0,K14/ABS(I14)) | M14: =IF(AND(ABS(L14)>=ThrPct,ABS(K14)>=ThrAmt),IF(K14<0,"Unfavorable","Favorable"),"")
A15: =Budget!A15 | B15: =Budget!B15 | C15: =Budget!C15 | D15: =Budget!D15 | E15: =INDEX(Budget!$E15:$P15,CurMonth) | F15: =INDEX(Actuals!$E15:$P15,CurMonth) | G15: =IF($D15="Revenue",F15-E15,E15-F15) | H15: =IF(E15=0,0,G15/ABS(E15)) | I15: =SUMPRODUCT(Budget!$E15:$P15*(Budget!$E$3:$P$3<=CurMonth)) | J15: =SUMPRODUCT(Actuals!$E15:$P15*(Budget!$E$3:$P$3<=CurMonth)) | K15: =IF($D15="Revenue",J15-I15,I15-J15) | L15: =IF(I15=0,0,K15/ABS(I15)) | M15: =IF(AND(ABS(L15)>=ThrPct,ABS(K15)>=ThrAmt),IF(K15<0,"Unfavorable","Favorable"),"")
... A24: =Budget!A24 | B24: =Budget!B24 | C24: =Budget!C24 | D24: =Budget!D24 | E24: =INDEX(Budget!$E24:$P24,CurMonth) | F24: =INDEX(Actuals!$E24:$P24,CurMonth) | G24: =IF($D24="Revenue",F24-E24,E24-F24) | H24: =IF(E24=0,0,G24/ABS(E24)) | I24: =SUMPRODUCT(Budget!$E24:$P24*(Budget!$E$3:$P$3<=CurMonth)) | J24: =SUMPRODUCT(Actuals!$E24:$P24*(Budget!$E$3:$P$3<=CurMonth)) | K24: =IF($D24="Revenue",J24-I24,I24-J24) | L24: =IF(I24=0,0,K24/ABS(I24)) | M24: =IF(AND(ABS(L24)>=ThrPct,ABS(K24)>=ThrAmt),IF(K24<0,"Unfavorable","Favorable"),"")

Sheet Forecast
A1: Rolling Forecast ($000s)
A2: Closed months = actuals. Open months use the line's method (blue, editable).
A3: ID | B3: Line item | C3: Department | D3: Category | E3: Method | F3: 1 | G3: 2 | H3: 3 | I3: 4 | J3: 5 | K3: 6 | L3: 7 | M3: 8 | N3: 9 | O3: 10 | P3: 11 | Q3: 12 | R3: FY Forecast | S3: FY Budget | T3: FY Var Fav/(Unfav) | U3: FY Var % | V3: YTD Actual | W3: YTD Budget | X3: YTD Attainment | Y3: 3-mo Run-rate
A4: =Budget!A4 | B4: =Budget!B4 | C4: =Budget!C4 | D4: =Budget!D4 | E4: Attainment | F4: =IF(F$3<=CurMonth,Actuals!E4,IF($E4="Attainment",Budget!E4*$X4,IF($E4="Run-rate",$Y4,Budget!E4))) | G4: =IF(G$3<=CurMonth,Actuals!F4,IF($E4="Attainment",Budget!F4*$X4,IF($E4="Run-rate",$Y4,Budget!F4))) | H4: =IF(H$3<=CurMonth,Actuals!G4,IF($E4="Attainment",Budget!G4*$X4,IF($E4="Run-rate",$Y4,Budget!G4))) | I4: =IF(I$3<=CurMonth,Actuals!H4,IF($E4="Attainment",Budget!H4*$X4,IF($E4="Run-rate",$Y4,Budget!H4))) | J4: =IF(J$3<=CurMonth,Actuals!I4,IF($E4="Attainment",Budget!I4*$X4,IF($E4="Run-rate",$Y4,Budget!I4))) | K4: =IF(K$3<=CurMonth,Actuals!J4,IF($E4="Attainment",Budget!J4*$X4,IF($E4="Run-rate",$Y4,Budget!J4))) | L4: =IF(L$3<=CurMonth,Actuals!K4,IF($E4="Attainment",Budget!K4*$X4,IF($E4="Run-rate",$Y4,Budget!K4))) | M4: =IF(M$3<=CurMonth,Actuals!L4,IF($E4="Attainment",Budget!L4*$X4,IF($E4="Run-rate",$Y4,Budget!L4))) | ... Q4: =IF(Q$3<=CurMonth,Actuals!P4,IF($E4="Attainment",Budget!P4*$X4,IF($E4="Run-rate",$Y4,Budget!P4))) | R4: =SUM(F4:Q4) | S4: =Budget!Q4 | T4: =IF($D4="Revenue",R4-S4,S4-R4) | U4: =IF(S4=0,0,T4/ABS(S4)) | V4: =SUMPRODUCT(Actuals!$E4:$P4*(Budget!$E$3:$P$3<=CurMonth)) | W4: =SUMPRODUCT(Budget!$E4:$P4*(Budget!$E$3:$P$3<=CurMonth)) | X4: =IF(W4=0,1,V4/W4) | Y4: =SUMPRODUCT(Actuals!$E4:$P4*(Budget!$E$3:$P$3>CurMonth-3)*(Budget!$E$3:$P$3<=CurMonth))/3
A5: =Budget!A5 | B5: =Budget!B5 | C5: =Budget!C5 | D5: =Budget!D5 | E5: Attainment | F5: =IF(F$3<=CurMonth,Actuals!E5,IF($E5="Attainment",Budget!E5*$X5,IF($E5="Run-rate",$Y5,Budget!E5))) | G5: =IF(G$3<=CurMonth,Actuals!F5,IF($E5="Attainment",Budget!F5*$X5,IF($E5="Run-rate",$Y5,Budget!F5))) | H5: =IF(H$3<=CurMonth,Actuals!G5,IF($E5="Attainment",Budget!G5*$X5,IF($E5="Run-rate",$Y5,Budget!G5))) | I5: =IF(I$3<=CurMonth,Actuals!H5,IF($E5="Attainment",Budget!H5*$X5,IF($E5="Run-rate",$Y5,Budget!H5))) | J5: =IF(J$3<=CurMonth,Actuals!I5,IF($E5="Attainment",Budget!I5*$X5,IF($E5="Run-rate",$Y5,Budget!I5))) | K5: =IF(K$3<=CurMonth,Actuals!J5,IF($E5="Attainment",Budget!J5*$X5,IF($E5="Run-rate",$Y5,Budget!J5))) | L5: =IF(L$3<=CurMonth,Actuals!K5,IF($E5="Attainment",Budget!K5*$X5,IF($E5="Run-rate",$Y5,Budget!K5))) | M5: =IF(M$3<=CurMonth,Actuals!L5,IF($E5="Attainment",Budget!L5*$X5,IF($E5="Run-rate",$Y5,Budget!L5))) | ... Q5: =IF(Q$3<=CurMonth,Actuals!P5,IF($E5="Attainment",Budget!P5*$X5,IF($E5="Run-rate",$Y5,Budget!P5))) | R5: =SUM(F5:Q5) | S5: =Budget!Q5 | T5: =IF($D5="Revenue",R5-S5,S5-R5) | U5: =IF(S5=0,0,T5/ABS(S5)) | V5: =SUMPRODUCT(Actuals!$E5:$P5*(Budget!$E$3:$P$3<=CurMonth)) | W5: =SUMPRODUCT(Budget!$E5:$P5*(Budget!$E$3:$P$3<=CurMonth)) | X5: =IF(W5=0,1,V5/W5) | Y5: =SUMPRODUCT(Actuals!$E5:$P5*(Budget!$E$3:$P$3>CurMonth-3)*(Budget!$E$3:$P$3<=CurMonth))/3
A6: =Budget!A6 | B6: =Budget!B6 | C6: =Budget!C6 | D6: =Budget!D6 | E6: Attainment | F6: =IF(F$3<=CurMonth,Actuals!E6,IF($E6="Attainment",Budget!E6*$X6,IF($E6="Run-rate",$Y6,Budget!E6))) | G6: =IF(G$3<=CurMonth,Actuals!F6,IF($E6="Attainment",Budget!F6*$X6,IF($E6="Run-rate",$Y6,Budget!F6))) | H6: =IF(H$3<=CurMonth,Actuals!G6,IF($E6="Attainment",Budget!G6*$X6,IF($E6="Run-rate",$Y6,Budget!G6))) | I6: =IF(I$3<=CurMonth,Actuals!H6,IF($E6="Attainment",Budget!H6*$X6,IF($E6="Run-rate",$Y6,Budget!H6))) | J6: =IF(J$3<=CurMonth,Actuals!I6,IF($E6="Attainment",Budget!I6*$X6,IF($E6="Run-rate",$Y6,Budget!I6))) | K6: =IF(K$3<=CurMonth,Actuals!J6,IF($E6="Attainment",Budget!J6*$X6,IF($E6="Run-rate",$Y6,Budget!J6))) | L6: =IF(L$3<=CurMonth,Actuals!K6,IF($E6="Attainment",Budget!K6*$X6,IF($E6="Run-rate",$Y6,Budget!K6))) | M6: =IF(M$3<=CurMonth,Actuals!L6,IF($E6="Attainment",Budget!L6*$X6,IF($E6="Run-rate",$Y6,Budget!L6))) | ... Q6: =IF(Q$3<=CurMonth,Actuals!P6,IF($E6="Attainment",Budget!P6*$X6,IF($E6="Run-rate",$Y6,Budget!P6))) | R6: =SUM(F6:Q6) | S6: =Budget!Q6 | T6: =IF($D6="Revenue",R6-S6,S6-R6) | U6: =IF(S6=0,0,T6/ABS(S6)) | V6: =SUMPRODUCT(Actuals!$E6:$P6*(Budget!$E$3:$P$3<=CurMonth)) | W6: =SUMPRODUCT(Budget!$E6:$P6*(Budget!$E$3:$P$3<=CurMonth)) | X6: =IF(W6=0,1,V6/W6) | Y6: =SUMPRODUCT(Actuals!$E6:$P6*(Budget!$E$3:$P$3>CurMonth-3)*(Budget!$E$3:$P$3<=CurMonth))/3
A7: =Budget!A7 | B7: =Budget!B7 | C7: =Budget!C7 | D7: =Budget!D7 | E7: Attainment | F7: =IF(F$3<=CurMonth,Actuals!E7,IF($E7="Attainment",Budget!E7*$X7,IF($E7="Run-rate",$Y7,Budget!E7))) | G7: =IF(G$3<=CurMonth,Actuals!F7,IF($E7="Attainment",Budget!F7*$X7,IF($E7="Run-rate",$Y7,Budget!F7))) | H7: =IF(H$3<=CurMonth,Actuals!G7,IF($E7="Attainment",Budget!G7*$X7,IF($E7="Run-rate",$Y7,Budget!G7))) | I7: =IF(I$3<=CurMonth,Actuals!H7,IF($E7="Attainment",Budget!H7*$X7,IF($E7="Run-rate",$Y7,Budget!H7))) | J7: =IF(J$3<=CurMonth,Actuals!I7,IF($E7="Attainment",Budget!I7*$X7,IF($E7="Run-rate",$Y7,Budget!I7))) | K7: =IF(K$3<=CurMonth,Actuals!J7,IF($E7="Attainment",Budget!J7*$X7,IF($E7="Run-rate",$Y7,Budget!J7))) | L7: =IF(L$3<=CurMonth,Actuals!K7,IF($E7="Attainment",Budget!K7*$X7,IF($E7="Run-rate",$Y7,Budget!K7))) | M7: =IF(M$3<=CurMonth,Actuals!L7,IF($E7="Attainment",Budget!L7*$X7,IF($E7="Run-rate",$Y7,Budget!L7))) | ... Q7: =IF(Q$3<=CurMonth,Actuals!P7,IF($E7="Attainment",Budget!P7*$X7,IF($E7="Run-rate",$Y7,Budget!P7))) | R7: =SUM(F7:Q7) | S7: =Budget!Q7 | T7: =IF($D7="Revenue",R7-S7,S7-R7) | U7: =IF(S7=0,0,T7/ABS(S7)) | V7: =SUMPRODUCT(Actuals!$E7:$P7*(Budget!$E$3:$P$3<=CurMonth)) | W7: =SUMPRODUCT(Budget!$E7:$P7*(Budget!$E$3:$P$3<=CurMonth)) | X7: =IF(W7=0,1,V7/W7) | Y7: =SUMPRODUCT(Actuals!$E7:$P7*(Budget!$E$3:$P$3>CurMonth-3)*(Budget!$E$3:$P$3<=CurMonth))/3
A8: =Budget!A8 | B8: =Budget!B8 | C8: =Budget!C8 | D8: =Budget!D8 | E8: Attainment | F8: =IF(F$3<=CurMonth,Actuals!E8,IF($E8="Attainment",Budget!E8*$X8,IF($E8="Run-rate",$Y8,Budget!E8))) | G8: =IF(G$3<=CurMonth,Actuals!F8,IF($E8="Attainment",Budget!F8*$X8,IF($E8="Run-rate",$Y8,Budget!F8))) | H8: =IF(H$3<=CurMonth,Actuals!G8,IF($E8="Attainment",Budget!G8*$X8,IF($E8="Run-rate",$Y8,Budget!G8))) | I8: =IF(I$3<=CurMonth,Actuals!H8,IF($E8="Attainment",Budget!H8*$X8,IF($E8="Run-rate",$Y8,Budget!H8))) | J8: =IF(J$3<=CurMonth,Actuals!I8,IF($E8="Attainment",Budget!I8*$X8,IF($E8="Run-rate",$Y8,Budget!I8))) | K8: =IF(K$3<=CurMonth,Actuals!J8,IF($E8="Attainment",Budget!J8*$X8,IF($E8="Run-rate",$Y8,Budget!J8))) | L8: =IF(L$3<=CurMonth,Actuals!K8,IF($E8="Attainment",Budget!K8*$X8,IF($E8="Run-rate",$Y8,Budget!K8))) | M8: =IF(M$3<=CurMonth,Actuals!L8,IF($E8="Attainment",Budget!L8*$X8,IF($E8="Run-rate",$Y8,Budget!L8))) | ... Q8: =IF(Q$3<=CurMonth,Actuals!P8,IF($E8="Attainment",Budget!P8*$X8,IF($E8="Run-rate",$Y8,Budget!P8))) | R8: =SUM(F8:Q8) | S8: =Budget!Q8 | T8: =IF($D8="Revenue",R8-S8,S8-R8) | U8: =IF(S8=0,0,T8/ABS(S8)) | V8: =SUMPRODUCT(Actuals!$E8:$P8*(Budget!$E$3:$P$3<=CurMonth)) | W8: =SUMPRODUCT(Budget!$E8:$P8*(Budget!$E$3:$P$3<=CurMonth)) | X8: =IF(W8=0,1,V8/W8) | Y8: =SUMPRODUCT(Actuals!$E8:$P8*(Budget!$E$3:$P$3>CurMonth-3)*(Budget!$E$3:$P$3<=CurMonth))/3
A9: =Budget!A9 | B9: =Budget!B9 | C9: =Budget!C9 | D9: =Budget!D9 | E9: Attainment | F9: =IF(F$3<=CurMonth,Actuals!E9,IF($E9="Attainment",Budget!E9*$X9,IF($E9="Run-rate",$Y9,Budget!E9))) | G9: =IF(G$3<=CurMonth,Actuals!F9,IF($E9="Attainment",Budget!F9*$X9,IF($E9="Run-rate",$Y9,Budget!F9))) | H9: =IF(H$3<=CurMonth,Actuals!G9,IF($E9="Attainment",Budget!G9*$X9,IF($E9="Run-rate",$Y9,Budget!G9))) | I9: =IF(I$3<=CurMonth,Actuals!H9,IF($E9="Attainment",Budget!H9*$X9,IF($E9="Run-rate",$Y9,Budget!H9))) | J9: =IF(J$3<=CurMonth,Actuals!I9,IF($E9="Attainment",Budget!I9*$X9,IF($E9="Run-rate",$Y9,Budget!I9))) | K9: =IF(K$3<=CurMonth,Actuals!J9,IF($E9="Attainment",Budget!J9*$X9,IF($E9="Run-rate",$Y9,Budget!J9))) | L9: =IF(L$3<=CurMonth,Actuals!K9,IF($E9="Attainment",Budget!K9*$X9,IF($E9="Run-rate",$Y9,Budget!K9))) | M9: =IF(M$3<=CurMonth,Actuals!L9,IF($E9="Attainment",Budget!L9*$X9,IF($E9="Run-rate",$Y9,Budget!L9))) | ... Q9: =IF(Q$3<=CurMonth,Actuals!P9,IF($E9="Attainment",Budget!P9*$X9,IF($E9="Run-rate",$Y9,Budget!P9))) | R9: =SUM(F9:Q9) | S9: =Budget!Q9 | T9: =IF($D9="Revenue",R9-S9,S9-R9) | U9: =IF(S9=0,0,T9/ABS(S9)) | V9: =SUMPRODUCT(Actuals!$E9:$P9*(Budget!$E$3:$P$3<=CurMonth)) | W9: =SUMPRODUCT(Budget!$E9:$P9*(Budget!$E$3:$P$3<=CurMonth)) | X9: =IF(W9=0,1,V9/W9) | Y9: =SUMPRODUCT(Actuals!$E9:$P9*(Budget!$E$3:$P$3>CurMonth-3)*(Budget!$E$3:$P$3<=CurMonth))/3
A10: =Budget!A10 | B10: =Budget!B10 | C10: =Budget!C10 | D10: =Budget!D10 | E10: Attainment | F10: =IF(F$3<=CurMonth,Actuals!E10,IF($E10="Attainment",Budget!E10*$X10,IF($E10="Run-rate",$Y10,Budget!E10))) | G10: =IF(G$3<=CurMonth,Actuals!F10,IF($E10="Attainment",Budget!F10*$X10,IF($E10="Run-rate",$Y10,Budget!F10))) | H10: =IF(H$3<=CurMonth,Actuals!G10,IF($E10="Attainment",Budget!G10*$X10,IF($E10="Run-rate",$Y10,Budget!G10))) | I10: =IF(I$3<=CurMonth,Actuals!H10,IF($E10="Attainment",Budget!H10*$X10,IF($E10="Run-rate",$Y10,Budget!H10))) | J10: =IF(J$3<=CurMonth,Actuals!I10,IF($E10="Attainment",Budget!I10*$X10,IF($E10="Run-rate",$Y10,Budget!I10))) | K10: =IF(K$3<=CurMonth,Actuals!J10,IF($E10="Attainment",Budget!J10*$X10,IF($E10="Run-rate",$Y10,Budget!J10))) | L10: =IF(L$3<=CurMonth,Actuals!K10,IF($E10="Attainment",Budget!K10*$X10,IF($E10="Run-rate",$Y10,Budget!K10))) | M10: =IF(M$3<=CurMonth,Actuals!L10,IF($E10="Attainment",Budget!L10*$X10,IF($E10="Run-rate",$Y10,Budget!L10))) | ... Q10: =IF(Q$3<=CurMonth,Actuals!P10,IF($E10="Attainment",Budget!P10*$X10,IF($E10="Run-rate",$Y10,Budget!P10))) | R10: =SUM(F10:Q10) | S10: =Budget!Q10 | T10: =IF($D10="Revenue",R10-S10,S10-R10) | U10: =IF(S10=0,0,T10/ABS(S10)) | V10: =SUMPRODUCT(Actuals!$E10:$P10*(Budget!$E$3:$P$3<=CurMonth)) | W10: =SUMPRODUCT(Budget!$E10:$P10*(Budget!$E$3:$P$3<=CurMonth)) | X10: =IF(W10=0,1,V10/W10) | Y10: =SUMPRODUCT(Actuals!$E10:$P10*(Budget!$E$3:$P$3>CurMonth-3)*(Budget!$E$3:$P$3<=CurMonth))/3
A11: =Budget!A11 | B11: =Budget!B11 | C11: =Budget!C11 | D11: =Budget!D11 | E11: Run-rate | F11: =IF(F$3<=CurMonth,Actuals!E11,IF($E11="Attainment",Budget!E11*$X11,IF($E11="Run-rate",$Y11,Budget!E11))) | G11: =IF(G$3<=CurMonth,Actuals!F11,IF($E11="Attainment",Budget!F11*$X11,IF($E11="Run-rate",$Y11,Budget!F11))) | H11: =IF(H$3<=CurMonth,Actuals!G11,IF($E11="Attainment",Budget!G11*$X11,IF($E11="Run-rate",$Y11,Budget!G11))) | I11: =IF(I$3<=CurMonth,Actuals!H11,IF($E11="Attainment",Budget!H11*$X11,IF($E11="Run-rate",$Y11,Budget!H11))) | J11: =IF(J$3<=CurMonth,Actuals!I11,IF($E11="Attainment",Budget!I11*$X11,IF($E11="Run-rate",$Y11,Budget!I11))) | K11: =IF(K$3<=CurMonth,Actuals!J11,IF($E11="Attainment",Budget!J11*$X11,IF($E11="Run-rate",$Y11,Budget!J11))) | L11: =IF(L$3<=CurMonth,Actuals!K11,IF($E11="Attainment",Budget!K11*$X11,IF($E11="Run-rate",$Y11,Budget!K11))) | M11: =IF(M$3<=CurMonth,Actuals!L11,IF($E11="Attainment",Budget!L11*$X11,IF($E11="Run-rate",$Y11,Budget!L11))) | ... Q11: =IF(Q$3<=CurMonth,Actuals!P11,IF($E11="Attainment",Budget!P11*$X11,IF($E11="Run-rate",$Y11,Budget!P11))) | R11: =SUM(F11:Q11) | S11: =Budget!Q11 | T11: =IF($D11="Revenue",R11-S11,S11-R11) | U11: =IF(S11=0,0,T11/ABS(S11)) | V11: =SUMPRODUCT(Actuals!$E11:$P11*(Budget!$E$3:$P$3<=CurMonth)) | W11: =SUMPRODUCT(Budget!$E11:$P11*(Budget!$E$3:$P$3<=CurMonth)) | X11: =IF(W11=0,1,V11/W11) | Y11: =SUMPRODUCT(Actuals!$E11:$P11*(Budget!$E$3:$P$3>CurMonth-3)*(Budget!$E$3:$P$3<=CurMonth))/3
A12: =Budget!A12 | B12: =Budget!B12 | C12: =Budget!C12 | D12: =Budget!D12 | E12: Attainment | F12: =IF(F$3<=CurMonth,Actuals!E12,IF($E12="Attainment",Budget!E12*$X12,IF($E12="Run-rate",$Y12,Budget!E12))) | G12: =IF(G$3<=CurMonth,Actuals!F12,IF($E12="Attainment",Budget!F12*$X12,IF($E12="Run-rate",$Y12,Budget!F12))) | H12: =IF(H$3<=CurMonth,Actuals!G12,IF($E12="Attainment",Budget!G12*$X12,IF($E12="Run-rate",$Y12,Budget!G12))) | I12: =IF(I$3<=CurMonth,Actuals!H12,IF($E12="Attainment",Budget!H12*$X12,IF($E12="Run-rate",$Y12,Budget!H12))) | J12: =IF(J$3<=CurMonth,Actuals!I12,IF($E12="Attainment",Budget!I12*$X12,IF($E12="Run-rate",$Y12,Budget!I12))) | K12: =IF(K$3<=CurMonth,Actuals!J12,IF($E12="Attainment",Budget!J12*$X12,IF($E12="Run-rate",$Y12,Budget!J12))) | L12: =IF(L$3<=CurMonth,Actuals!K12,IF($E12="Attainment",Budget!K12*$X12,IF($E12="Run-rate",$Y12,Budget!K12))) | M12: =IF(M$3<=CurMonth,Actuals!L12,IF($E12="Attainment",Budget!L12*$X12,IF($E12="Run-rate",$Y12,Budget!L12))) | ... Q12: =IF(Q$3<=CurMonth,Actuals!P12,IF($E12="Attainment",Budget!P12*$X12,IF($E12="Run-rate",$Y12,Budget!P12))) | R12: =SUM(F12:Q12) | S12: =Budget!Q12 | T12: =IF($D12="Revenue",R12-S12,S12-R12) | U12: =IF(S12=0,0,T12/ABS(S12)) | V12: =SUMPRODUCT(Actuals!$E12:$P12*(Budget!$E$3:$P$3<=CurMonth)) | W12: =SUMPRODUCT(Budget!$E12:$P12*(Budget!$E$3:$P$3<=CurMonth)) | X12: =IF(W12=0,1,V12/W12) | Y12: =SUMPRODUCT(Actuals!$E12:$P12*(Budget!$E$3:$P$3>CurMonth-3)*(Budget!$E$3:$P$3<=CurMonth))/3
A13: =Budget!A13 | B13: =Budget!B13 | C13: =Budget!C13 | D13: =Budget!D13 | E13: Run-rate | F13: =IF(F$3<=CurMonth,Actuals!E13,IF($E13="Attainment",Budget!E13*$X13,IF($E13="Run-rate",$Y13,Budget!E13))) | G13: =IF(G$3<=CurMonth,Actuals!F13,IF($E13="Attainment",Budget!F13*$X13,IF($E13="Run-rate",$Y13,Budget!F13))) | H13: =IF(H$3<=CurMonth,Actuals!G13,IF($E13="Attainment",Budget!G13*$X13,IF($E13="Run-rate",$Y13,Budget!G13))) | I13: =IF(I$3<=CurMonth,Actuals!H13,IF($E13="Attainment",Budget!H13*$X13,IF($E13="Run-rate",$Y13,Budget!H13))) | J13: =IF(J$3<=CurMonth,Actuals!I13,IF($E13="Attainment",Budget!I13*$X13,IF($E13="Run-rate",$Y13,Budget!I13))) | K13: =IF(K$3<=CurMonth,Actuals!J13,IF($E13="Attainment",Budget!J13*$X13,IF($E13="Run-rate",$Y13,Budget!J13))) | L13: =IF(L$3<=CurMonth,Actuals!K13,IF($E13="Attainment",Budget!K13*$X13,IF($E13="Run-rate",$Y13,Budget!K13))) | M13: =IF(M$3<=CurMonth,Actuals!L13,IF($E13="Attainment",Budget!L13*$X13,IF($E13="Run-rate",$Y13,Budget!L13))) | ... Q13: =IF(Q$3<=CurMonth,Actuals!P13,IF($E13="Attainment",Budget!P13*$X13,IF($E13="Run-rate",$Y13,Budget!P13))) | R13: =SUM(F13:Q13) | S13: =Budget!Q13 | T13: =IF($D13="Revenue",R13-S13,S13-R13) | U13: =IF(S13=0,0,T13/ABS(S13)) | V13: =SUMPRODUCT(Actuals!$E13:$P13*(Budget!$E$3:$P$3<=CurMonth)) | W13: =SUMPRODUCT(Budget!$E13:$P13*(Budget!$E$3:$P$3<=CurMonth)) | X13: =IF(W13=0,1,V13/W13) | Y13: =SUMPRODUCT(Actuals!$E13:$P13*(Budget!$E$3:$P$3>CurMonth-3)*(Budget!$E$3:$P$3<=CurMonth))/3
A14: =Budget!A14 | B14: =Budget!B14 | C14: =Budget!C14 | D14: =Budget!D14 | E14: Run-rate | F14: =IF(F$3<=CurMonth,Actuals!E14,IF($E14="Attainment",Budget!E14*$X14,IF($E14="Run-rate",$Y14,Budget!E14))) | G14: =IF(G$3<=CurMonth,Actuals!F14,IF($E14="Attainment",Budget!F14*$X14,IF($E14="Run-rate",$Y14,Budget!F14))) | H14: =IF(H$3<=CurMonth,Actuals!G14,IF($E14="Attainment",Budget!G14*$X14,IF($E14="Run-rate",$Y14,Budget!G14))) | I14: =IF(I$3<=CurMonth,Actuals!H14,IF($E14="Attainment",Budget!H14*$X14,IF($E14="Run-rate",$Y14,Budget!H14))) | J14: =IF(J$3<=CurMonth,Actuals!I14,IF($E14="Attainment",Budget!I14*$X14,IF($E14="Run-rate",$Y14,Budget!I14))) | K14: =IF(K$3<=CurMonth,Actuals!J14,IF($E14="Attainment",Budget!J14*$X14,IF($E14="Run-rate",$Y14,Budget!J14))) | L14: =IF(L$3<=CurMonth,Actuals!K14,IF($E14="Attainment",Budget!K14*$X14,IF($E14="Run-rate",$Y14,Budget!K14))) | M14: =IF(M$3<=CurMonth,Actuals!L14,IF($E14="Attainment",Budget!L14*$X14,IF($E14="Run-rate",$Y14,Budget!L14))) | ... Q14: =IF(Q$3<=CurMonth,Actuals!P14,IF($E14="Attainment",Budget!P14*$X14,IF($E14="Run-rate",$Y14,Budget!P14))) | R14: =SUM(F14:Q14) | S14: =Budget!Q14 | T14: =IF($D14="Revenue",R14-S14,S14-R14) | U14: =IF(S14=0,0,T14/ABS(S14)) | V14: =SUMPRODUCT(Actuals!$E14:$P14*(Budget!$E$3:$P$3<=CurMonth)) | W14: =SUMPRODUCT(Budget!$E14:$P14*(Budget!$E$3:$P$3<=CurMonth)) | X14: =IF(W14=0,1,V14/W14) | Y14: =SUMPRODUCT(Actuals!$E14:$P14*(Budget!$E$3:$P$3>CurMonth-3)*(Budget!$E$3:$P$3<=CurMonth))/3
A15: =Budget!A15 | B15: =Budget!B15 | C15: =Budget!C15 | D15: =Budget!D15 | E15: Run-rate | F15: =IF(F$3<=CurMonth,Actuals!E15,IF($E15="Attainment",Budget!E15*$X15,IF($E15="Run-rate",$Y15,Budget!E15))) | G15: =IF(G$3<=CurMonth,Actuals!F15,IF($E15="Attainment",Budget!F15*$X15,IF($E15="Run-rate",$Y15,Budget!F15))) | H15: =IF(H$3<=CurMonth,Actuals!G15,IF($E15="Attainment",Budget!G15*$X15,IF($E15="Run-rate",$Y15,Budget!G15))) | I15: =IF(I$3<=CurMonth,Actuals!H15,IF($E15="Attainment",Budget!H15*$X15,IF($E15="Run-rate",$Y15,Budget!H15))) | J15: =IF(J$3<=CurMonth,Actuals!I15,IF($E15="Attainment",Budget!I15*$X15,IF($E15="Run-rate",$Y15,Budget!I15))) | K15: =IF(K$3<=CurMonth,Actuals!J15,IF($E15="Attainment",Budget!J15*$X15,IF($E15="Run-rate",$Y15,Budget!J15))) | L15: =IF(L$3<=CurMonth,Actuals!K15,IF($E15="Attainment",Budget!K15*$X15,IF($E15="Run-rate",$Y15,Budget!K15))) | M15: =IF(M$3<=CurMonth,Actuals!L15,IF($E15="Attainment",Budget!L15*$X15,IF($E15="Run-rate",$Y15,Budget!L15))) | ... Q15: =IF(Q$3<=CurMonth,Actuals!P15,IF($E15="Attainment",Budget!P15*$X15,IF($E15="Run-rate",$Y15,Budget!P15))) | R15: =SUM(F15:Q15) | S15: =Budget!Q15 | T15: =IF($D15="Revenue",R15-S15,S15-R15) | U15: =IF(S15=0,0,T15/ABS(S15)) | V15: =SUMPRODUCT(Actuals!$E15:$P15*(Budget!$E$3:$P$3<=CurMonth)) | W15: =SUMPRODUCT(Budget!$E15:$P15*(Budget!$E$3:$P$3<=CurMonth)) | X15: =IF(W15=0,1,V15/W15) | Y15: =SUMPRODUCT(Actuals!$E15:$P15*(Budget!$E$3:$P$3>CurMonth-3)*(Budget!$E$3:$P$3<=CurMonth))/3
... A24: =Budget!A24 | B24: =Budget!B24 | C24: =Budget!C24 | D24: =Budget!D24 | E24: Run-rate | F24: =IF(F$3<=CurMonth,Actuals!E24,IF($E24="Attainment",Budget!E24*$X24,IF($E24="Run-rate",$Y24,Budget!E24))) | G24: =IF(G$3<=CurMonth,Actuals!F24,IF($E24="Attainment",Budget!F24*$X24,IF($E24="Run-rate",$Y24,Budget!F24))) | H24: =IF(H$3<=CurMonth,Actuals!G24,IF($E24="Attainment",Budget!G24*$X24,IF($E24="Run-rate",$Y24,Budget!G24))) | I24: =IF(I$3<=CurMonth,Actuals!H24,IF($E24="Attainment",Budget!H24*$X24,IF($E24="Run-rate",$Y24,Budget!H24))) | J24: =IF(J$3<=CurMonth,Actuals!I24,IF($E24="Attainment",Budget!I24*$X24,IF($E24="Run-rate",$Y24,Budget!I24))) | K24: =IF(K$3<=CurMonth,Actuals!J24,IF($E24="Attainment",Budget!J24*$X24,IF($E24="Run-rate",$Y24,Budget!J24))) | L24: =IF(L$3<=CurMonth,Actuals!K24,IF($E24="Attainment",Budget!K24*$X24,IF($E24="Run-rate",$Y24,Budget!K24))) | M24: =IF(M$3<=CurMonth,Actuals!L24,IF($E24="Attainment",Budget!L24*$X24,IF($E24="Run-rate",$Y24,Budget!L24))) | ... Q24: =IF(Q$3<=CurMonth,Actuals!P24,IF($E24="Attainment",Budget!P24*$X24,IF($E24="Run-rate",$Y24,Budget!P24))) | R24: =SUM(F24:Q24) | S24: =Budget!Q24 | T24: =IF($D24="Revenue",R24-S24,S24-R24) | U24: =IF(S24=0,0,T24/ABS(S24)) | V24: =SUMPRODUCT(Actuals!$E24:$P24*(Budget!$E$3:$P$3<=CurMonth)) | W24: =SUMPRODUCT(Budget!$E24:$P24*(Budget!$E$3:$P$3<=CurMonth)) | X24: =IF(W24=0,1,V24/W24) | Y24: =SUMPRODUCT(Actuals!$E24:$P24*(Budget!$E$3:$P$3>CurMonth-3)*(Budget!$E$3:$P$3<=CurMonth))/3

Sheet P&L Summary
A1: P&L Summary ($000s)
A2: ="YTD through "&Inputs!B8&" and full-year forecast vs. budget"
A3: Line | B3: Sign | C3: YTD Budget | D3: YTD Actual | E3: YTD Var Fav/(Unfav) | F3: YTD Var % | G3: FY Budget | H3: FY Forecast | I3: FY Var Fav/(Unfav) | J3: FY Var %
A4: Revenue | B4: 1 | C4: =SUMIFS(BvA!$I$4:$I$24,BvA!$D$4:$D$24,"Revenue") | D4: =SUMIFS(BvA!$J$4:$J$24,BvA!$D$4:$D$24,"Revenue") | E4: =B4*(D4-C4) | F4: =IF(C4=0,0,E4/ABS(C4)) | G4: =SUMIFS(Forecast!$S$4:$S$24,BvA!$D$4:$D$24,"Revenue") | H4: =SUMIFS(Forecast!$R$4:$R$24,BvA!$D$4:$D$24,"Revenue") | I4: =B4*(H4-G4) | J4: =IF(G4=0,0,I4/ABS(G4))
A5: COGS | B5: -1 | C5: =SUMIFS(BvA!$I$4:$I$24,BvA!$D$4:$D$24,"COGS") | D5: =SUMIFS(BvA!$J$4:$J$24,BvA!$D$4:$D$24,"COGS") | E5: =B5*(D5-C5) | F5: =IF(C5=0,0,E5/ABS(C5)) | G5: =SUMIFS(Forecast!$S$4:$S$24,BvA!$D$4:$D$24,"COGS") | H5: =SUMIFS(Forecast!$R$4:$R$24,BvA!$D$4:$D$24,"COGS") | I5: =B5*(H5-G5) | J5: =IF(G5=0,0,I5/ABS(G5))
A6: Gross Profit | B6: 1 | C6: =C4-C5 | D6: =D4-D5 | E6: =B6*(D6-C6) | F6: =IF(C6=0,0,E6/ABS(C6)) | G6: =G4-G5 | H6: =H4-H5 | I6: =B6*(H6-G6) | J6: =IF(G6=0,0,I6/ABS(G6))
A7: Gross Margin % | B7: 0 | C7: =IF(C4=0,0,C6/C4) | D7: =IF(D4=0,0,D6/D4) | E7: =D7-C7 | G7: =IF(G4=0,0,G6/G4) | H7: =IF(H4=0,0,H6/H4) | I7: =H7-G7
A8: Opex - Sales | B8: -1 | C8: =SUMIFS(BvA!$I$4:$I$24,BvA!$D$4:$D$24,"Opex",BvA!$C$4:$C$24,"Sales") | D8: =SUMIFS(BvA!$J$4:$J$24,BvA!$D$4:$D$24,"Opex",BvA!$C$4:$C$24,"Sales") | E8: =B8*(D8-C8) | F8: =IF(C8=0,0,E8/ABS(C8)) | G8: =SUMIFS(Forecast!$S$4:$S$24,BvA!$D$4:$D$24,"Opex",BvA!$C$4:$C$24,"Sales") | H8: =SUMIFS(Forecast!$R$4:$R$24,BvA!$D$4:$D$24,"Opex",BvA!$C$4:$C$24,"Sales") | I8: =B8*(H8-G8) | J8: =IF(G8=0,0,I8/ABS(G8))
A9: Opex - Marketing | B9: -1 | C9: =SUMIFS(BvA!$I$4:$I$24,BvA!$D$4:$D$24,"Opex",BvA!$C$4:$C$24,"Marketing") | D9: =SUMIFS(BvA!$J$4:$J$24,BvA!$D$4:$D$24,"Opex",BvA!$C$4:$C$24,"Marketing") | E9: =B9*(D9-C9) | F9: =IF(C9=0,0,E9/ABS(C9)) | G9: =SUMIFS(Forecast!$S$4:$S$24,BvA!$D$4:$D$24,"Opex",BvA!$C$4:$C$24,"Marketing") | H9: =SUMIFS(Forecast!$R$4:$R$24,BvA!$D$4:$D$24,"Opex",BvA!$C$4:$C$24,"Marketing") | I9: =B9*(H9-G9) | J9: =IF(G9=0,0,I9/ABS(G9))
A10: Opex - Operations | B10: -1 | C10: =SUMIFS(BvA!$I$4:$I$24,BvA!$D$4:$D$24,"Opex",BvA!$C$4:$C$24,"Operations") | D10: =SUMIFS(BvA!$J$4:$J$24,BvA!$D$4:$D$24,"Opex",BvA!$C$4:$C$24,"Operations") | E10: =B10*(D10-C10) | F10: =IF(C10=0,0,E10/ABS(C10)) | G10: =SUMIFS(Forecast!$S$4:$S$24,BvA!$D$4:$D$24,"Opex",BvA!$C$4:$C$24,"Operations") | H10: =SUMIFS(Forecast!$R$4:$R$24,BvA!$D$4:$D$24,"Opex",BvA!$C$4:$C$24,"Operations") | I10: =B10*(H10-G10) | J10: =IF(G10=0,0,I10/ABS(G10))
A11: Opex - G&A | B11: -1 | C11: =SUMIFS(BvA!$I$4:$I$24,BvA!$D$4:$D$24,"Opex",BvA!$C$4:$C$24,"G&A") | D11: =SUMIFS(BvA!$J$4:$J$24,BvA!$D$4:$D$24,"Opex",BvA!$C$4:$C$24,"G&A") | E11: =B11*(D11-C11) | F11: =IF(C11=0,0,E11/ABS(C11)) | G11: =SUMIFS(Forecast!$S$4:$S$24,BvA!$D$4:$D$24,"Opex",BvA!$C$4:$C$24,"G&A") | H11: =SUMIFS(Forecast!$R$4:$R$24,BvA!$D$4:$D$24,"Opex",BvA!$C$4:$C$24,"G&A") | I11: =B11*(H11-G11) | J11: =IF(G11=0,0,I11/ABS(G11))
A12: Opex - IT | B12: -1 | C12: =SUMIFS(BvA!$I$4:$I$24,BvA!$D$4:$D$24,"Opex",BvA!$C$4:$C$24,"IT") | D12: =SUMIFS(BvA!$J$4:$J$24,BvA!$D$4:$D$24,"Opex",BvA!$C$4:$C$24,"IT") | E12: =B12*(D12-C12) | F12: =IF(C12=0,0,E12/ABS(C12)) | G12: =SUMIFS(Forecast!$S$4:$S$24,BvA!$D$4:$D$24,"Opex",BvA!$C$4:$C$24,"IT") | H12: =SUMIFS(Forecast!$R$4:$R$24,BvA!$D$4:$D$24,"Opex",BvA!$C$4:$C$24,"IT") | I12: =B12*(H12-G12) | J12: =IF(G12=0,0,I12/ABS(G12))
A13: Total Opex | B13: -1 | C13: =SUM(C8:C12) | D13: =SUM(D8:D12) | E13: =B13*(D13-C13) | F13: =IF(C13=0,0,E13/ABS(C13)) | G13: =SUM(G8:G12) | H13: =SUM(H8:H12) | I13: =B13*(H13-G13) | J13: =IF(G13=0,0,I13/ABS(G13))
A14: EBITDA | B14: 1 | C14: =C6-C13 | D14: =D6-D13 | E14: =B14*(D14-C14) | F14: =IF(C14=0,0,E14/ABS(C14)) | G14: =G6-G13 | H14: =H6-H13 | I14: =B14*(H14-G14) | J14: =IF(G14=0,0,I14/ABS(G14))
A15: EBITDA Margin % | B15: 0 | C15: =IF(C4=0,0,C14/C4) | D15: =IF(D4=0,0,D14/D4) | E15: =D15-C15 | G15: =IF(G4=0,0,G14/G4) | H15: =IF(H4=0,0,H14/H4) | I15: =H15-G15

Sheet Mgmt Report
A1: Management Report - Northwind Supply Co.
A2: ="FY2026 performance through "&Inputs!B8&" close"
A4: Key metric | B4: Budget | C4: Actual / Forecast | D4: Var Fav/(Unfav) | E4: Var %
A5: YTD Revenue | B5: ='P&L Summary'!C4 | C5: ='P&L Summary'!D4 | D5: ='P&L Summary'!E4 | E5: ='P&L Summary'!F4
A6: YTD Gross Margin % | B6: ='P&L Summary'!C7 | C6: ='P&L Summary'!D7 | D6: ='P&L Summary'!E7
A7: YTD EBITDA | B7: ='P&L Summary'!C14 | C7: ='P&L Summary'!D14 | D7: ='P&L Summary'!E14 | E7: ='P&L Summary'!F14
A8: FY Revenue (forecast) | B8: ='P&L Summary'!G4 | C8: ='P&L Summary'!H4 | D8: ='P&L Summary'!I4 | E8: ='P&L Summary'!J4
A9: FY EBITDA (forecast) | B9: ='P&L Summary'!G14 | C9: ='P&L Summary'!H14 | D9: ='P&L Summary'!I14 | E9: ='P&L Summary'!J14
A10: FY EBITDA Margin % (forecast) | B10: ='P&L Summary'!G15 | C10: ='P&L Summary'!H15 | D10: ='P&L Summary'!I15
A12: Flagged YTD variances (from BvA) | B12: =COUNTIF(BvA!M:M,"Unfavorable")&" unfavorable, "&COUNTIF(BvA!M:M,"Favorable")&" favorable"
A14: Commentary (September close)
A15: 1. YTD EBITDA is $1,102k vs. $1,482k budget ($380k / 26% unfavorable). Full-year EBITDA is forecast at $1,715k vs. $2,150k budget.
A16: 2. Safety Equipment revenue is $695k (7%) below budget YTD after a distributor contract was lost in June. Its cost of goods shows $377k favorable, but only because volume fell; the net gross profit impact is about -$318k. Action: replacement distributor pipeline and pricing review.
A17: 3. Industrial Supplies revenue is ahead of budget after the April price increase and is forecast $623k favorable for the year, partly offsetting Safety Equipment.
A18: 4. Freight & Logistics is $139k (14%) unfavorable YTD following a carrier rate increase in March, rising faster than shipment volume. Action: re-bid carrier contracts before Q1.
A19: 5. Trade Shows & Events is $185k over budget from an unbudgeted May trade show; Professional Fees are $118k over from one-off August legal and audit work. Both are treated as non-recurring in the forecast.
A20: 6. Operations and IT salaries are $189k favorable from hiring lags through July. Positions are now filled, so this favorability should not be counted on for Q4.

Sheet Checks
A1: Integrity checks
A2: Every check must be TRUE before the report is distributed.
A3: Check | B3: Result
A4: Closed months in the forecast equal actuals | B4: =ABS(SUMPRODUCT((Forecast!F3:Q3<=CurMonth)*(Forecast!F4:Q24-Actuals!E4:P24)))<0.001
A5: No missing actuals in closed months | B5: =SUMPRODUCT((Actuals!E3:P3<=CurMonth)*(Actuals!E4:P24=""))=0
A6: No actuals entered for open months | B6: =SUMPRODUCT((Actuals!E3:P3>CurMonth)*(Actuals!E4:P24<>""))=0
A7: P&L FY budget revenue ties to Budget sheet | B7: =ABS('P&L Summary'!G4-SUMIFS(Budget!Q4:Q24,Budget!D4:D24,"Revenue"))<0.001
A8: P&L YTD actual EBITDA ties to line-level BvA | B8: =ABS('P&L Summary'!D14-(SUMIFS(BvA!J4:J24,BvA!D4:D24,"Revenue")-SUMIFS(BvA!J4:J24,BvA!D4:D24,"<>Revenue")))<0.001
A9: FY forecast = YTD actual + open-month forecast (all lines) | B9: =ABS(SUM(Forecast!R4:R24)-SUM(Forecast!V4:V24)-SUMPRODUCT((Forecast!F3:Q3>CurMonth)*Forecast!F4:Q24))<0.001
A10: Opex by department sums to total opex lines | B10: =ABS('P&L Summary'!D13-SUMIFS(BvA!J4:J24,BvA!D4:D24,"Opex"))<0.001
A12: ALL CHECKS PASS | B12: =AND(B4:B10)
